pyeasysocket/__init__.py
pyeasysocket/base.py
pyeasysocket/tcp.py
pyeasysocket/udp.py
pyeasysocket-1.0.0.dist-info/LICENSE
pyeasysocket-1.0.0.dist-info/METADATA
pyeasysocket-1.0.0.dist-info/WHEEL
pyeasysocket-1.0.0.dist-info/top_level.txt
pyeasysocket-1.0.0.dist-info/RECORD
